LICENSE
MANIFEST.in
README.md
requirements.txt
setup.cfg
setup.py
Quart_Keycloak.egg-info/PKG-INFO
Quart_Keycloak.egg-info/SOURCES.txt
Quart_Keycloak.egg-info/dependency_links.txt
Quart_Keycloak.egg-info/not-zip-safe
Quart_Keycloak.egg-info/requires.txt
Quart_Keycloak.egg-info/top_level.txt
quart_keycloak/__init__.py
quart_keycloak/openid.py
quart_keycloak/utils.py